{
  "skinnerbox": {
    "name": "Skinnerbox",
    "description": "A box with a small rat that periodically generates satisfaction by clicking a button.",
    "complexDescription": "Generates 0.1 satisfaction per second.",
    "baseCost": 10
  },
  "gup": {
    "name": "Gup",
    "description": "A small cat that generates satisfaction by purring.",
    "complexDescription": "Generates 1 satisfaction per second.",
    "baseCost": 100
  },
  "monkey": {
    "name": "Monkey",
    "description": "A monkey with a typewriter.", 
    "complexDescription": "This monkey generates satisfaction at random when it completes one of it's great works.",
    "baseCost": 10000
  },
  "rpg": {
    "name": "RPG",
    "description": "The new hit roleplaying game.",
    "complexDescription": "Satisfaction gained fluctuates in a sinewave because of player uptime.",
    "baseCost": 50000
  }
}
